[
  {
    "name": "Эксплуатация",
    "variants": [
      {
        "name": "Для личного использования",
        "coefficient": 1
      },
      {
        "name": "Такси",
        "coefficient": 1.2
      },
      {
        "name": "Перевозки внутри страны",
        "coefficient": 1.3
      },
      {
        "name": "Международные перевозки",
        "coefficient": 1.5
      },
      {
        "name": "В учебных целях",
        "coefficient": 1.3
      }
    ]
  },
  {
    "name": "Стаж вождения и возраст",
    "variants": [
      {
        "name": "Менее 2 лет, младше 25",
        "coefficient": 1.2
      },
      {
        "name": "Менее 2 лет, старше 25",
        "coefficient": 1.1
      },
      {
        "name": "Более 2 лет, младше 25",
        "coefficient": 1.1
      },
      {
        "name": "Более 2 лет, старше 25",
        "coefficient": 0.95
      }
    ]
  },
  {
    "name": "Тип топлива, объём двигателя",
    "variants": [
      {
        "name": "Бензин до 1.2",
        "coefficient": 0.95
      },
      {
        "name": "Бензин 1.2-1.8",
        "coefficient": 1
      },
      {
        "name": "Бензин 1.8-2.5",
        "coefficient": 1.1
      },
      {
        "name": "Бензин 2.5 и более",
        "coefficient": 1.3
      },
      {
        "name": "Дизель до 1.2",
        "coefficient": 0.95
      },
      {
        "name": "Дизель 1.2-1.8",
        "coefficient": 1.05
      },
      {
        "name": "Дизель 1.8-2.5",
        "coefficient": 1.15
      },
      {
        "name": "Дизель 2.5 и более",
        "coefficient": 1.35
      }
    ]
  }
]